elevation/__init__.py
elevation/route.py
route_elevation-0.0.2.dist-info/METADATA
route_elevation-0.0.2.dist-info/WHEEL
route_elevation-0.0.2.dist-info/top_level.txt
route_elevation-0.0.2.dist-info/RECORD
