Metadata-Version: 2.1
Name: route-elevation
Version: 0.0.2
Requires-Dist: googlemaps
